NetMonitor/__init__.py
NetMonitor/data_analysis.py
NetMonitor/data_collection.py
NetMonitor/utils.py
NetMonitor/visualization.py
network_performance_analysis-0.1.0.dist-info/LICENSE
network_performance_analysis-0.1.0.dist-info/METADATA
network_performance_analysis-0.1.0.dist-info/WHEEL
network_performance_analysis-0.1.0.dist-info/entry_points.txt
network_performance_analysis-0.1.0.dist-info/top_level.txt
network_performance_analysis-0.1.0.dist-info/RECORD
